beproud.django.commons-0.42-py3.8-nspkg.pth
beproud/django/commons/__init__.py
beproud/django/commons/forms/__init__.py
beproud/django/commons/forms/decorators.py
beproud/django/commons/forms/fields.py
beproud/django/commons/forms/forms.py
beproud/django/commons/forms/utils.py
beproud/django/commons/http/__init__.py
beproud/django/commons/management/__init__.py
beproud/django/commons/management/commands/__init__.py
beproud/django/commons/management/commands/rmcache.py
beproud/django/commons/middleware/__init__.py
beproud/django/commons/middleware/debug.py
beproud/django/commons/models/__init__.py
beproud/django/commons/models/admin.py
beproud/django/commons/models/base.py
beproud/django/commons/models/fields.py
beproud/django/commons/models/utils.py
beproud/django/commons/shortcuts/__init__.py
beproud/django/commons/templatetags/__init__.py
beproud/django/commons/templatetags/compat.py
beproud/django/commons/templatetags/datetime_tags.py
beproud/django/commons/templatetags/googlead_tags.py
beproud/django/commons/templatetags/html_tags.py
beproud/django/commons/templatetags/string_tags.py
beproud/django/commons/test/__init__.py
beproud/django/commons/test/simple.py
beproud/django/commons/utils/__init__.py
beproud/django/commons/utils/cache.py
beproud/django/commons/utils/dbi.py
beproud/django/commons/utils/image.py
beproud/django/commons/utils/javascript.py
beproud/django/commons/utils/template.py
beproud/django/commons/utils/timeutils.py
beproud/django/commons/views/__init__.py
beproud/django/commons/views/classes.py
beproud/django/commons/views/decorators.py
beproud/django/commons/views/simple.py
beproud.django.commons-0.42.dist-info/LICENSE
beproud.django.commons-0.42.dist-info/METADATA
beproud.django.commons-0.42.dist-info/WHEEL
beproud.django.commons-0.42.dist-info/namespace_packages.txt
beproud.django.commons-0.42.dist-info/top_level.txt
beproud.django.commons-0.42.dist-info/RECORD
